LICENSE.txt
MANIFEST.in
README.rst
setup.cfg
setup.py
gdsync/__init__.py
gdsync.egg-info/PKG-INFO
gdsync.egg-info/SOURCES.txt
gdsync.egg-info/dependency_links.txt
gdsync.egg-info/entry_points.txt
gdsync.egg-info/requires.txt
gdsync.egg-info/top_level.txt
gdsync/cli/__init__.py
gdsync/cli/cli.py
gdsync/google/__init__.py
gdsync/google/drive.py
gdsync/google/finished_folders.py
gdsync/google/sync.py