Metadata-Version: 1.0
Name: gdsync
Version: 0.0.11
Summary: Google Drive Synchronizer
Home-page: https://github.com/uuum/gdsync
Author: Masato Bito
Author-email: bito_m@uuum.jp
License: MIT
Platform: UNKNOWN
